<?xml version="1.0" encoding="ISO-8859-1"?>
<!-- Generator: ControlBuild -->

<MODEL_REQUIREMENTS>
	<FUNCTIONAL_TREE TYPE="mac">
		<CHILDREN>
			<NODE NAME="flow" MODEL_PATH="Standard\equipment_library\flow_compute">
			</NODE>
			<NODE NAME="syrupManagement" MODEL_PATH="Applications\batch\syrup_weighing">
			</NODE>
			<NODE NAME="arrivalValveSyrup1" MODEL_PATH="Standard\io_library\io_on_off_valve">
			</NODE>
			<NODE NAME="arrivalValveSyrup2" MODEL_PATH="Standard\io_library\io_on_off_valve">
			</NODE>
			<NODE NAME="arrivalValveSyrup3" MODEL_PATH="Standard\io_library\io_on_off_valve">
			</NODE>
			<NODE NAME="syrupExtractionValve" MODEL_PATH="Standard\io_library\io_on_off_valve">
			</NODE>
			<NODE NAME="faults" TYPE="rel">
			</NODE>
			<NODE NAME="syrupQuantity" MODEL_PATH="Applications\batch\add_syrup">
			</NODE>
			<NODE NAME="syrupsTank" MODEL_PATH="Standard\equipment_library\tank">
			</NODE>
			<NODE NAME="level" MODEL_PATH="Standard\equipment_library\analog_sensor">
			</NODE>
			<NODE NAME="scale" MODEL_PATH="Standard\equipment_library\bounded_scale">
			</NODE>
		</CHILDREN>
	</FUNCTIONAL_TREE>
</MODEL_REQUIREMENTS>